<root version="2638">
	<item Name="defaultprofession" Key="" Value="1" Channel="0" Service="0" />
	<item Name="defaultbackground" Key="" Value="1" Channel="0" Service="0" />
	<item Name="generatedirectattribute" Key="" Value="9" Channel="0" Service="0" />
	<item Name="generaterandattribute" Key="" Value="2" Channel="0" Service="0" />
	<item Name="maxdip" Key="" Value="1000" Channel="0" Service="0" />
	<item Name="maxherocount" Key="" Value="12" Channel="0" Service="0" />
	<item Name="maxherolevel" Key="" Value="30" Channel="0" Service="0" />
	<item Name="maxactivecount" Key="" Value="20" Channel="0" Service="0" />
	<item Name="maxinnatecount" Key="" Value="4" Channel="0" Service="0" />
	<item Name="useinnatecount" Key="" Value="2" Channel="0" Service="0" />
	<item Name="maxcharactercount" Key="" Value="20" Channel="0" Service="0" />
	<item Name="maxheroteamcount" Key="" Value="8" Channel="0" Service="0" />
	<item Name="recruitinitcount" Key="" Value="2" Channel="0" Service="0" />
	<item Name="recruitmaxcount" Key="" Value="10" Channel="0" Service="0" />
	<item Name="recruitrefresh" Key="" Value="21600" Channel="0" Service="0" />
	<item Name="maxhp_bar" Key="" Value="200" Channel="0" Service="0" />
	<item Name="maxatk_bar" Key="" Value="150" Channel="0" Service="0" />
	<item Name="maxdef_bar" Key="" Value="100" Channel="0" Service="0" />
	<item Name="maxres_bar" Key="" Value="100" Channel="0" Service="0" />
	<item Name="maxtal_bar" Key="" Value="60" Channel="0" Service="0" />
	<item Name="maxspd_bar" Key="" Value="50" Channel="0" Service="0" />
	<item Name="maxluk_bar" Key="" Value="60" Channel="0" Service="0" />
	<item Name="maxmov_bar" Key="" Value="6" Channel="0" Service="0" />
	<item Name="buildskininitid" Key="" Value="1" Channel="0" Service="0" />
	<item Name="maxDamage_bar" Key="" Value="106" Channel="0" Service="0" />
	<item Name="maxAR_bar" Key="" Value="100" Channel="0" Service="0" />
	<item Name="maxCRT_bar" Key="" Value="100" Channel="0" Service="0" />
	<item Name="herolistbuildid" Key="" Value="200" Channel="0" Service="0" />
	<item Name="transferleveloffest" Key="" Value="4" Channel="0" Service="0" />
	<item Name="Powercoefficient_B" Key="" Value="0" Channel="0" Service="0" />
	<item Name="initclinicnum" Key="" Value="200" Channel="0" Service="0" />
	<item Name="initgranarynum" Key="" Value="100" Channel="0" Service="0" />
	<item Name="initsmithynum" Key="" Value="100" Channel="0" Service="0" />
	<item Name="roledurability_pve" Key="" Value="50" Channel="0" Service="0" />
	<item Name="roledurability_pveconsume" Key="" Value="1" Channel="0" Service="0" />
	<item Name="buildupgrademaxnum" Key="" Value="2" Channel="0" Service="0" />
	<item Name="roledeath_characterpool" Key="" Value="4069001" Channel="0" Service="0" />
	<item Name="heronamelength" Key="" Value="40" Channel="0" Service="0" />
	<item Name="exploregrainwarningcount" Key="" Value="50" Channel="0" Service="0" />
</root>